{
  "@context": {
    "schema": "http://schema.org/",
    "regen": "http://regen.network/",
    "regen:additionalCertifications": { "@container": "@list" }
  },
  "@type": "regen:C01-CreditBatch",
  "regen:vcsRetirementSerialNumber": "9381-93664744-93664774-VCS-VCU-259-VER-KE-14-612-01012019-31122019-1",
  "regen:vcsProjectId": 612,
  "regen:additionalCertifications": [
    {
      "schema:name": "CCB-Biodiversity Gold",
      "schema:url": {
        "@type": "schema:URL",
        "@value": "https://verra.org/project/ccb-program/"
      }
    },
    {
      "schema:name": "CCB-Climate Gold",
      "schema:url": {
        "@type": "schema:URL",
        "@value": "https://verra.org/project/ccb-program/"
      }
    }
  ]
}
