{
  "@context": {
    "schema": "http://schema.org/",
    "regen": "http://regen.network/",
    "xsd": "http://www.w3.org/2001/XMLSchema#",
    "dash": "http://datashapes.org/dash#"
  },
  "@type": "regen:CreditClass",
  "schema:description": "",
  "regen:sourceRegistry": {
    "schema:name": "",
    "schema:url": {
      "@type": "schema:URL",
      "@value": ""
    }
  },
  "regen:sectoralScope": [
    {
      "@type": "xsd:string",
      "@value": ""
    }
  ],
  "regen:offsetGenerationMethod": [
    {
      "@type": "xsd:string",
      "@value": ""
    }
  ],
  "regen:approvedMethodologies": {
    "@type": "schema:BreadcrumbList",
    "schema:itemListElement": [
      {
        "@type": "regen:Methodology",
        "schema:name": "",
        "schema:url": {
          "@type": "schema:URL",
          "@value": ""
        }
      },
      {
        "@type": "regen:Methodology",
        "schema:name": "",
        "schema:url": {
          "@type": "schema:URL",
          "@value": ""
        }
      }
    ],
    "schema:url": {
      "@type": "schema:URL",
      "@value": "http://bar.com"
    } 
  },
  "regen:verificationMethod": ""
}
